{
  "loader": "yet_another_industrialization:multiblock",
  "ref": {
    "a": {
      "Name": "undergarden:veil_mushroom_stem"
    },
    "b": {
      "Name": "undergarden:veil_mushroom_cap"
    },
    "c": {
      "Name": "undergarden:mushroom_veil",
      "Properties": {
        "east": "false",
        "end": "true",
        "north": "true",
        "south": "false",
        "up": "false",
        "west": "true"
      }
    },
    "d": {
      "Name": "undergarden:mushroom_veil",
      "Properties": {
        "east": "false",
        "end": "false",
        "north": "true",
        "south": "false",
        "up": "false",
        "west": "false"
      }
    },
    "e": {
      "Name": "undergarden:mushroom_veil",
      "Properties": {
        "east": "true",
        "end": "false",
        "north": "true",
        "south": "false",
        "up": "false",
        "west": "false"
      }
    },
    "f": {
      "Name": "undergarden:mushroom_veil",
      "Properties": {
        "east": "false",
        "end": "true",
        "north": "false",
        "south": "true",
        "up": "false",
        "west": "true"
      }
    },
    "g": {
      "Name": "undergarden:mushroom_veil",
      "Properties": {
        "east": "false",
        "end": "false",
        "north": "true",
        "south": "false",
        "up": "true",
        "west": "true"
      }
    },
    "h": {
      "Name": "undergarden:mushroom_veil",
      "Properties": {
        "east": "false",
        "end": "false",
        "north": "true",
        "south": "false",
        "up": "false",
        "west": "true"
      }
    },
    "i": {
      "Name": "undergarden:mushroom_veil",
      "Properties": {
        "east": "true",
        "end": "true",
        "north": "true",
        "south": "false",
        "up": "false",
        "west": "false"
      }
    },
    "j": {
      "Name": "undergarden:mushroom_veil",
      "Properties": {
        "east": "true",
        "end": "false",
        "north": "true",
        "south": "false",
        "up": "true",
        "west": "false"
      }
    },
    "k": {
      "Name": "undergarden:mushroom_veil",
      "Properties": {
        "east": "false",
        "end": "false",
        "north": "false",
        "south": "true",
        "up": "false",
        "west": "true"
      }
    },
    "l": {
      "Name": "undergarden:mushroom_veil",
      "Properties": {
        "east": "false",
        "end": "true",
        "north": "false",
        "south": "true",
        "up": "false",
        "west": "false"
      }
    },
    "m": {
      "Name": "undergarden:mushroom_veil",
      "Properties": {
        "east": "true",
        "end": "true",
        "north": "false",
        "south": "true",
        "up": "false",
        "west": "false"
      }
    },
    "n": {
      "Name": "undergarden:mushroom_veil",
      "Properties": {
        "east": "false",
        "end": "false",
        "north": "false",
        "south": "true",
        "up": "false",
        "west": "false"
      }
    },
    "o": {
      "Name": "undergarden:mushroom_veil",
      "Properties": {
        "east": "true",
        "end": "false",
        "north": "false",
        "south": "true",
        "up": "false",
        "west": "false"
      }
    },
    "p": {
      "Name": "undergarden:mushroom_veil",
      "Properties": {
        "east": "false",
        "end": "false",
        "north": "true",
        "south": "false",
        "up": "true",
        "west": "false"
      }
    },
    "q": {
      "Name": "undergarden:mushroom_veil",
      "Properties": {
        "east": "false",
        "end": "false",
        "north": "false",
        "south": "true",
        "up": "true",
        "west": "true"
      }
    },
    "r": {
      "Name": "undergarden:mushroom_veil",
      "Properties": {
        "east": "false",
        "end": "false",
        "north": "false",
        "south": "true",
        "up": "true",
        "west": "false"
      }
    },
    "s": {
      "Name": "undergarden:mushroom_veil",
      "Properties": {
        "east": "true",
        "end": "false",
        "north": "false",
        "south": "true",
        "up": "true",
        "west": "false"
      }
    },
    "t": {
      "Name": "undergarden:mushroom_veil",
      "Properties": {
        "east": "false",
        "end": "true",
        "north": "false",
        "south": "false",
        "up": "false",
        "west": "true"
      }
    },
    "u": {
      "Name": "undergarden:mushroom_veil",
      "Properties": {
        "east": "false",
        "end": "false",
        "north": "false",
        "south": "false",
        "up": "false",
        "west": "true"
      }
    },
    "v": {
      "Name": "undergarden:mushroom_veil",
      "Properties": {
        "east": "true",
        "end": "true",
        "north": "false",
        "south": "false",
        "up": "false",
        "west": "false"
      }
    },
    "w": {
      "Name": "undergarden:mushroom_veil",
      "Properties": {
        "east": "true",
        "end": "false",
        "north": "false",
        "south": "false",
        "up": "false",
        "west": "false"
      }
    },
    "x": {
      "Name": "undergarden:mushroom_veil",
      "Properties": {
        "east": "false",
        "end": "false",
        "north": "false",
        "south": "false",
        "up": "true",
        "west": "true"
      }
    },
    "y": {
      "Name": "undergarden:mushroom_veil",
      "Properties": {
        "east": "false",
        "end": "true",
        "north": "true",
        "south": "false",
        "up": "false",
        "west": "false"
      }
    },
    "z": {
      "Name": "undergarden:mushroom_veil",
      "Properties": {
        "east": "true",
        "end": "false",
        "north": "false",
        "south": "false",
        "up": "true",
        "west": "false"
      }
    }
  },
  "shape": [
    [
      "       ",
      "       ",
      "       ",
      "       ",
      " bbbbb ",
      "       ",
      "       ",
      "       ",
      "       ",
      "       "
    ],
    [
      "       ",
      "       ",
      "       ",
      "  bbb  ",
      "bbjzsbb",
      "  ewo  ",
      "  ivm  ",
      "       ",
      "       ",
      "       "
    ],
    [
      "       ",
      "  bbb  ",
      "  bbb  ",
      " bb bb ",
      "bj   sb",
      " e   o ",
      " i   m ",
      "       ",
      "       ",
      "       "
    ],
    [
      "   b   ",
      "  bab  ",
      "  bab  ",
      " b a b ",
      "bp a rb",
      " d a n ",
      " d a l ",
      " d a   ",
      " y a   ",
      "   a   "
    ],
    [
      "       ",
      "  bbb  ",
      "  bbb  ",
      " bb bb ",
      "bg   qb",
      " h   k ",
      " h   k ",
      " c   f ",
      "       ",
      "       "
    ],
    [
      "       ",
      "       ",
      "       ",
      "  bbb  ",
      "bbgxqbb",
      "  huk  ",
      "  huk  ",
      "  ctf  ",
      "       ",
      "       "
    ],
    [
      "       ",
      "       ",
      "       ",
      "       ",
      " bbbbb ",
      "       ",
      "       ",
      "       ",
      "       ",
      "       "
    ]
  ],
  "version": 4
}