{
  "loader": "yet_another_industrialization:multiblock",
  "ref": {
    "a": {
      "Name": "minecraft:oak_log",
      "Properties": {
        "axis": "y"
      }
    },
    "b": {
      "Name": "herbsandharvest:fruit_leaves",
      "Properties": {
        "distance": "3",
        "persistent": "false",
        "waterlogged": "false"
      }
    },
    "c": {
      "Name": "herbsandharvest:fruit_leaves",
      "Properties": {
        "distance": "2",
        "persistent": "false",
        "waterlogged": "false"
      }
    },
    "d": {
      "Name": "herbsandharvest:fruit_leaves",
      "Properties": {
        "distance": "1",
        "persistent": "false",
        "waterlogged": "false"
      }
    },
    "e": {
      "Name": "herbsandharvest:peach_fruit_leaves",
      "Properties": {
        "age": "0",
        "distance": "3",
        "persistent": "false",
        "waterlogged": "false"
      }
    },
    "f": {
      "Name": "herbsandharvest:peach_fruit_leaves",
      "Properties": {
        "age": "0",
        "distance": "4",
        "persistent": "false",
        "waterlogged": "false"
      }
    },
    "g": {
      "Name": "herbsandharvest:fruit_leaves",
      "Properties": {
        "distance": "4",
        "persistent": "false",
        "waterlogged": "false"
      }
    },
    "h": {
      "Name": "herbsandharvest:peach_fruit_leaves",
      "Properties": {
        "age": "0",
        "distance": "2",
        "persistent": "false",
        "waterlogged": "false"
      }
    },
    "i": {
      "Name": "herbsandharvest:peach_fruit_leaves",
      "Properties": {
        "age": "0",
        "distance": "1",
        "persistent": "false",
        "waterlogged": "false"
      }
    }
  },
  "shape": [
    [
      "     ",
      " fef ",
      " bcb ",
      " gbf ",
      "     ",
      "     ",
      "     "
    ],
    [
      "  e  ",
      "gbcbg",
      "bcdce",
      "gbcbg",
      "  h  ",
      "     ",
      "     "
    ],
    [
      " bhe ",
      "bcdcb",
      "hiaic",
      "bcacb",
      " cac ",
      "  a  ",
      "  a  "
    ],
    [
      "  b  ",
      "fbcbg",
      "ecdcb",
      "gehbg",
      "  h  ",
      "     ",
      "     "
    ],
    [
      "     ",
      " gbg ",
      " bcb ",
      " gbg ",
      "     ",
      "     ",
      "     "
    ]
  ],
  "version": 4
}