{
  "loader": "yet_another_industrialization:multiblock",
  "ref": {
    "a": {
      "Name": "regions_unexplored:white_magnolia_leaves",
      "Properties": {
        "distance": "1",
        "persistent": "false",
        "waterlogged": "false"
      }
    },
    "b": {
      "Name": "regions_unexplored:magnolia_log",
      "Properties": {
        "axis": "y"
      }
    },
    "c": {
      "Name": "regions_unexplored:magnolia_log",
      "Properties": {
        "axis": "z"
      }
    },
    "d": {
      "Name": "regions_unexplored:magnolia_log",
      "Properties": {
        "axis": "x"
      }
    }
  },
  "shape": [
    [
      "            ",
      "            ",
      "      aaaaa ",
      "            ",
      "            ",
      "            ",
      "            "
    ],
    [
      "            ",
      "        aa  ",
      "     aaaaaaa",
      "        aa  ",
      "            ",
      "            ",
      "            "
    ],
    [
      "            ",
      "      aaaa  ",
      "     aaaaaaa",
      "      aaaa  ",
      "            ",
      "            ",
      "            "
    ],
    [
      "            ",
      "      aaaaa ",
      "     aaaaaaa",
      "      aacaa ",
      "            ",
      "            ",
      "            "
    ],
    [
      "            ",
      " aaaaa aaaa ",
      "     aaaaaaa",
      "       aaaa ",
      "      cc    ",
      "            ",
      "    b       "
    ],
    [
      "  aa        ",
      "aaaaaaaaa   ",
      "  aa aaaaaaa",
      "       aa   ",
      "            ",
      "     b      ",
      "     b      "
    ],
    [
      "  aaaa      ",
      "aaaaaaa     ",
      "  aaaaaaaaa ",
      "    b       ",
      "    b       ",
      "    b       ",
      "     d      "
    ],
    [
      " aaaaa      ",
      "aaaaaaa     ",
      " aabaa      ",
      "   b        ",
      "            ",
      "            ",
      "            "
    ],
    [
      " aaaa       ",
      "aaaaaaa     ",
      " aaaa       ",
      "            ",
      "            ",
      "            ",
      "            "
    ],
    [
      "   aa       ",
      "aaaaaaa     ",
      "   aa       ",
      "            ",
      "            ",
      "            ",
      "            "
    ],
    [
      "            ",
      " aaaaa      ",
      "            ",
      "            ",
      "            ",
      "            ",
      "            "
    ]
  ],
  "version": 4
}